aesel/AeselEventClient.py
aesel/AeselTransactionClient.py
aesel/__init__.py
aesel/model/AeselAction.py
aesel/model/AeselApplicationUser.py
aesel/model/AeselAssetCollection.py
aesel/model/AeselAssetMetadata.py
aesel/model/AeselAssetRelationship.py
aesel/model/AeselDataList.py
aesel/model/AeselGraphHandle.py
aesel/model/AeselObject.py
aesel/model/AeselObjectFrame.py
aesel/model/AeselProject.py
aesel/model/AeselProperty.py
aesel/model/AeselPropertyFrame.py
aesel/model/AeselPropertyValue.py
aesel/model/AeselScene.py
aesel/model/AeselSceneGroup.py
aesel/model/AeselSceneTransform.py
aesel/model/AeselUserDevice.py
aesel/model/__init__.py
python_aesel_client-0.8.dist-info/LICENSE
python_aesel_client-0.8.dist-info/METADATA
python_aesel_client-0.8.dist-info/WHEEL
python_aesel_client-0.8.dist-info/top_level.txt
python_aesel_client-0.8.dist-info/RECORD
