Metadata-Version: 2.1
Name: python-aesel-client
Version: 0.8
Summary: Python Aesel Client
Home-page: https://github.com/AO-StreetArt/PyAesel
Author: AO Street Art
Author-email: aostreetart9@gmail.com
License: Apache2
Platform: UNKNOWN
Requires-Dist: requests
Requires-Dist: cryptography
